miftahdb
