Metadata-Version: 2.1
Name: miftahdb
Version: 0.2.3
Summary: Easy-to-use synchronous/asynchronous key-value database backed by sqlite3.
Home-page: https://github.com/miftahDB/miftahdb-python
Author: vwh
Author-email: vwhe@proton.me
License: MIT
Project-URL: Source, https://github.com/miftahDB/miftahdb-python
Project-URL: Tracker, https://github.com/miftahDB/miftahdb-python/issues
Project-URL: Documentation, https://miftahdb.rtfd.io/
Keywords: sync,asyncio,sqlite,sqlite3,key-value,database,redis
Requires-Python: >=3.8
License-File: LICENSE
